README
setup.py
coverage_reporter/__init__.py
coverage_reporter/__main__.py
coverage_reporter/config.py
coverage_reporter/data.py
coverage_reporter/errors.py
coverage_reporter/plugins.py
coverage_reporter.egg-info/PKG-INFO
coverage_reporter.egg-info/SOURCES.txt
coverage_reporter.egg-info/dependency_links.txt
coverage_reporter.egg-info/top_level.txt
coverage_reporter/collectors/__init__.py
coverage_reporter/collectors/base.py
coverage_reporter/collectors/coverage_collector.py
coverage_reporter/collectors/figleaf_collector.py
coverage_reporter/collectors/util.py
coverage_reporter/filters/__init__.py
coverage_reporter/filters/exclude.py
coverage_reporter/filters/minimum.py
coverage_reporter/filters/patch.py
coverage_reporter/reports/__init__.py
coverage_reporter/reports/annotate.py
coverage_reporter/reports/summarize.py
scripts/coverage-reporter