Metadata-Version: 1.0
Name: coverage-reporter
Version: 0.01
Summary: Coverage reporting tool
Home-page: http://github.org/dugan/coverage-reporter/
Author: David Christian
Author-email: david.chrsitian@gmail.com
License: MIT
Platform: Posix; MacOS X; Windows
Classifier: Intended Audience :: Developers
Classifier: License :: OSI Approved :: MIT License
Classifier: Operating System :: OS Independent
